{
  "realhook": {
    "host": "192.168.4.153",
    "stat_port": "8089",
    "stat_path": "/cp_status"
  },
  "servers": [
    {
      "host": "192.168.4.3",
      "port": "80"
    }
  ],
  "cprules": [
    {
      "name": "login",
      "rule": [
        {
          "check": "$cs_uri_query",
          "pcre": "(?:si_n=YJDL)|(?:si_n=SY_DL)|(?:si_n=DL)"
        }
      ]
    },
    {
      "name": "llzk",
      "rule": [
        {
          "check": "$cs_uri_query",
          "pcre": "(?:nv=ZX_LLZKYH)"
        }
      ]
    },
    {
      "name": "rwk",
      "rule": [
        {
          "check": "$cs_uri_query",
          "pcre": "(?:nv=RWK)"
        }
      ]
    },
    {
      "name": "zdcx",
      "rule": [
        {
          "check": "$cs_uri_query",
          "pcre": "(?:nv=zdcx)"
        }
      ]
    },
    {
      "name": "xdcx",
      "rule": [
        {
          "check": "$cs_uri_query",
          "pcre": "(?:nv=xdcx)"
        }
      ]
    },
    {
      "name": "llcx",
      "rule": [
        {
          "check": "$cs_uri_query",
          "pcre": "(?:nv=llcx)"
        }
      ]
    },
    {
      "name": "4gfx",
      "rule": [
        {
          "check": "$cs_uri_query",
          "pcre": "(?:nv=4gfx)"
        }
      ]
    },
    {
      "name": "4gzx",
      "rule": [
        {
          "check": "$cs_uri_query",
          "pcre": "(?:nv=4gzx)"
        }
      ]
    },
    {
      "name": "all",
      "rule": [
        {
          "check": "$cs_uri_query",
          "pcre": ".*"
        }
      ]
    }
  ]
}
